.source MCClass.java
.class public MCClass
.super java.lang.Object

.method public static main([Ljava/lang/String;)V
.var 0 is args Ljava/lang/String; from Label0 to Label1
.var 1 is x I from Label0 to Label1
Label0:
	iconst_0
	istore_1
	iload_1
	iconst_5
	iadd
	istore_1
	iload_1
	bipush 10
	isub
	istore_1
	iload_1
	iconst_2
	ineg
	imul
	istore_1
	iload_1
	invokestatic io/string_of_int(I)Ljava/lang/String;
	invokestatic io/printStrLn(Ljava/lang/String;)V
	iload_1
	iconst_1
	iadd
	istore_1
	iload_1
	invokestatic io/string_of_int(I)Ljava/lang/String;
	invokestatic io/printStrLn(Ljava/lang/String;)V
	iload_1
	iconst_2
	idiv
	istore_1
	iload_1
	invokestatic io/string_of_int(I)Ljava/lang/String;
	invokestatic io/printStrLn(Ljava/lang/String;)V
	iload_1
	iconst_3
	irem
	istore_1
	iload_1
	invokestatic io/string_of_int(I)Ljava/lang/String;
	invokestatic io/printStrLn(Ljava/lang/String;)V
Label1:
	return
.limit stack 2
.limit locals 2
.end method
